betby/__init__.py
betby/margin.py
betby/markets.py
betby-0.3.59.dist-info/METADATA
betby-0.3.59.dist-info/WHEEL
betby-0.3.59.dist-info/top_level.txt
betby-0.3.59.dist-info/RECORD
